hooks_toolkit/asyncio_set_hook.py
hooks_toolkit/asyncio_xrpld.py
hooks_toolkit/libs/asyncio/keylet_utils/__init__.py
hooks_toolkit/libs/asyncio/keylet_utils/execution_utility.py
hooks_toolkit/libs/asyncio/keylet_utils/state_utility.py
hooks_toolkit/libs/asyncio/xrpl_helpers/__init__.py
hooks_toolkit/libs/asyncio/xrpl_helpers/fund_system.py
hooks_toolkit/libs/asyncio/xrpl_helpers/setup.py
hooks_toolkit/libs/asyncio/xrpl_helpers/tools.py
hooks_toolkit/libs/asyncio/xrpl_helpers/transaction.py
hooks_toolkit/libs/binary_models/__init__.py
hooks_toolkit/libs/binary_models/amount_model.py
hooks_toolkit/libs/binary_models/base_model.py
hooks_toolkit/libs/binary_models/test_model.py
hooks_toolkit/libs/binary_models/utils/__init__.py
hooks_toolkit/libs/binary_models/utils/decode.py
hooks_toolkit/libs/binary_models/utils/encode.py
hooks_toolkit/libs/binary_models/utils/types.py
hooks_toolkit/libs/keylet_utils/__init__.py
hooks_toolkit/libs/keylet_utils/execution_utility.py
hooks_toolkit/libs/keylet_utils/state_utility.py
hooks_toolkit/libs/xrpl_helpers/__init__.py
hooks_toolkit/libs/xrpl_helpers/constants.py
hooks_toolkit/libs/xrpl_helpers/fund_system.py
hooks_toolkit/libs/xrpl_helpers/server_url.py
hooks_toolkit/libs/xrpl_helpers/setup.py
hooks_toolkit/libs/xrpl_helpers/tools.py
hooks_toolkit/libs/xrpl_helpers/transaction.py
hooks_toolkit/models/grants.py
hooks_toolkit/models/parameters.py
hooks_toolkit/models/state.py
hooks_toolkit/set_hook.py
hooks_toolkit/types.py
hooks_toolkit/utils.py
hooks_toolkit/xrpld.py
hooks_toolkit-1.1.0.dist-info/METADATA
hooks_toolkit-1.1.0.dist-info/WHEEL
hooks_toolkit-1.1.0.dist-info/RECORD
