Metadata-Version: 2.1
Name: hooks-toolkit
Version: 1.1.0
Summary: 
Author: Denis Angell
Author-email: dangell@transia.co
Requires-Python: >=3.8,<4.0
Classifier: Programming Language :: Python :: 3
Classifier: Programming Language :: Python :: 3.8
Classifier: Programming Language :: Python :: 3.9
Classifier: Programming Language :: Python :: 3.10
Classifier: Programming Language :: Python :: 3.11
Classifier: Programming Language :: Python :: 3.12
Requires-Dist: python-dotenv (>=1.0.0,<2.0.0)
Requires-Dist: xahau-py (>=3.0.0,<4.0.0)
